AUTHORS.rst
CONTRIBUTING.rst
HISTORY.rst
LICENSE
MANIFEST.in
README.rst
setup.cfg
setup.py
test/test_fields.py
test/test_tinyobj.py
tinyobj/__init__.py
tinyobj/_compat.py
tinyobj/fields.py
tinyobj/tinyobj.py
tinyobj.egg-info/PKG-INFO
tinyobj.egg-info/SOURCES.txt
tinyobj.egg-info/dependency_links.txt
tinyobj.egg-info/not-zip-safe
tinyobj.egg-info/top_level.txt