Metadata-Version: 1.1
Name: tinyobj
Version: 0.1.0
Summary: a tiny dict -> object mapper
Home-page: https://github.com/BrianHicks/tinyobj
Author: Brian Hicks
Author-email: brian@brianthicks.com
License: MIT
Keywords: tinyobj
Platform: UNKNOWN
Classifier: Development Status :: 2 - Pre-Alpha
Classifier: Intended Audience :: Developers
Classifier: License :: OSI Approved :: MIT License
Classifier: Natural Language :: English
Classifier: Programming Language :: Python :: 2
Classifier: Programming Language :: Python :: 2.6
Classifier: Programming Language :: Python :: 2.7
Classifier: Programming Language :: Python :: 3
Classifier: Programming Language :: Python :: 3.3
Classifier: Programming Language :: Python :: Implementation :: PyPy
